LICENSE.txt
MANIFEST.in
README.md
requirements.txt
setup.py
skwadon/__init__.py
skwadon/action_lib.py
skwadon/aws.py
skwadon/aws_glue_connection.py
skwadon/aws_glue_crawler.py
skwadon/aws_glue_datacatalog.py
skwadon/aws_glue_job.py
skwadon/aws_glue_trigger.py
skwadon/aws_iam_group.py
skwadon/aws_iam_policy.py
skwadon/aws_iam_role.py
skwadon/aws_lambda.py
skwadon/aws_rds.py
skwadon/aws_redshift.py
skwadon/aws_s3_bucket.py
skwadon/aws_stepfunctions.py
skwadon/common_action.py
skwadon/lib.py
skwadon/main.py
skwadon/testcloud.py
skwadon.egg-info/PKG-INFO
skwadon.egg-info/SOURCES.txt
skwadon.egg-info/dependency_links.txt
skwadon.egg-info/entry_points.txt
skwadon.egg-info/requires.txt
skwadon.egg-info/top_level.txt