Metadata-Version: 1.0
Name: skwadon
Version: 0.0.2
Summary: skwadon
Home-page: https://github.com/suzuki-navi/skwadon
Author: suzuki-navi
Author-email: UNKNOWN
License: UNKNOWN
Platform: UNKNOWN
